gafofile/__init__.py
gafofile/gafoc.py
gafoxf-0.2.0.dist-info/licenses/LICENSE
gafoxf-0.2.0.dist-info/METADATA
gafoxf-0.2.0.dist-info/WHEEL
gafoxf-0.2.0.dist-info/top_level.txt
gafoxf-0.2.0.dist-info/RECORD
