Metadata-Version: 2.4
Name: GAFOXF
Version: 0.2.0
Summary: Custom compression library using GAFO algorithm
Home-page: https://github.com/yourusername/gafoxf
Author: Your Name
Classifier: Programming Language :: Python :: 3
Classifier: License :: OSI Approved :: MIT License
Classifier: Operating System :: OS Independent
Requires-Python: >=3.6
License-File: LICENSE
Dynamic: author
Dynamic: classifier
Dynamic: description
Dynamic: description-content-type
Dynamic: home-page
Dynamic: license-file
Dynamic: requires-python
Dynamic: summary
